upper_folder_getter/__init__.py
upper_folder_getter/upper_folder_getter.py
upper_folder_getter-0.1.0.dist-info/LICENSE
upper_folder_getter-0.1.0.dist-info/METADATA
upper_folder_getter-0.1.0.dist-info/WHEEL
upper_folder_getter-0.1.0.dist-info/top_level.txt
upper_folder_getter-0.1.0.dist-info/RECORD
