Metadata-Version: 2.1
Name: upper-folder-getter
Version: 0.1.0
Summary: ImportError workaround
Home-page: https://github.com/eonianmonk/AntiImportError
Author: Dima B
License: MIT
Platform: UNKNOWN
Classifier: Programming Language :: Python :: 3
Classifier: Operating System :: OS Independent
Requires-Python: >=3.6
